{
  "project_info": {
    "project_number": "630538886855",
    "project_id": "librarysearchapp",
    "storage_bucket": "librarysearchapp.firebasestorage.app"
  },
  "client": [
    {
      "client_info": {
        "mobilesdk_app_id": "1:630538886855:android:9e64b47d73684783bba8e2",
        "android_client_info": {
          "package_name": "com.example.flutter_application_8"
        }
      },
      "oauth_client": [],
      "api_key": [
        {
          "current_key": "AIzaSyAvHBx7XwICpjtH2iBSVeSy7v-8H_rXIu0"
        }
      ],
      "services": {
        "appinvite_service": {
          "other_platform_oauth_client": []
        }
      }
    }
  ],
  "configuration_version": "1"
}